easy_mongodb_auth_handler/__init__.py
easy_mongodb_auth_handler/auth.py
easy_mongodb_auth_handler/core_db.py
easy_mongodb_auth_handler/utils.py
easy_mongodb_auth_handler/package_functions/__init__.py
easy_mongodb_auth_handler/package_functions/func.py
easy_mongodb_auth_handler/package_functions/message.py
easy_mongodb_auth_handler-3.0.0.dist-info/licenses/LICENSE
easy_mongodb_auth_handler-3.0.0.dist-info/METADATA
easy_mongodb_auth_handler-3.0.0.dist-info/WHEEL
easy_mongodb_auth_handler-3.0.0.dist-info/top_level.txt
easy_mongodb_auth_handler-3.0.0.dist-info/RECORD
