Metadata-Version: 2.4
Name: easy_mongodb_auth_handler
Version: 3.0.0
Summary: A user authentication and verification system using MongoDB.
Home-page: https://github.com/lukbrew25/easy-mongodb-auth-handler/
Author: Lukbrew25
License: MIT
Classifier: Development Status :: 4 - Beta
Classifier: Intended Audience :: Developers
Classifier: Topic :: Internet
Classifier: Programming Language :: Python :: 3
Classifier: License :: OSI Approved :: MIT License
Classifier: Operating System :: OS Independent
Requires-Python: >=3.9
License-File: LICENSE
Requires-Dist: bcrypt>=4.0.0
Requires-Dist: certifi>=2025.6.15
Requires-Dist: pymongo>=4.6.3
Requires-Dist: python-dotenv>=1.1.1
Dynamic: author
Dynamic: classifier
Dynamic: description
Dynamic: description-content-type
Dynamic: home-page
Dynamic: license
Dynamic: license-file
Dynamic: requires-dist
Dynamic: requires-python
Dynamic: summary
